matrix_array/__init__.py
matrix_array/array.py
matrix_array-0.1.0.dist-info/DESCRIPTION.rst
matrix_array-0.1.0.dist-info/METADATA
matrix_array-0.1.0.dist-info/RECORD
matrix_array-0.1.0.dist-info/WHEEL
matrix_array-0.1.0.dist-info/metadata.json
matrix_array-0.1.0.dist-info/top_level.txt
utils/__init__.py
utils/parser.py
